webplane/__init__.py
webplane/_version.py
webplane/colors.py
webplane/request.py
webplane/webapp.py
webplane/logging/__init__.py
webplane/logging/formatter.py
webplane/logging/tokenizer.py
webplane-0.0.0.dist-info/LICENSE
webplane-0.0.0.dist-info/METADATA
webplane-0.0.0.dist-info/WHEEL
webplane-0.0.0.dist-info/entry_points.txt
webplane-0.0.0.dist-info/top_level.txt
webplane-0.0.0.dist-info/RECORD
