Metadata-Version: 2.1
Name: webplane
Version: 0.0.0
Summary: WebEngine
Home-page: https://github.com/webplane/webplane
Author: João Pinto
Author-email: lamego.pinto@gmail.com
License: BSD-3
Platform: UNKNOWN
Requires-Dist: cherrypy
Requires-Dist: enclosed
